{"table":{"properties":{"Name":"urn:xdaq-flashlist:hostInfo","LastUpdate":"Wed, Aug 16 2023 08:22:54 GMT","Version":"$Revision: 15125 $","Tag":"unit","LastOriginator":"http://srv-s2b18-27-01.cms:9999/urn:xdaq-application:lid=5","Rows":14},"definition":[{"key":"context","type":"string"},{"key":"cpuUsage","type":"double"},{"key":"sessionid","type":"string"},{"key":"timestamp","type":"time"}],"rows":[{"context":"http://srv-s2b18-31-01.cms:9999","cpuUsage":1.13214667589156e+00,"sessionid":"","timestamp":"2023-08-16T08:22:51.185898Z"},{"context":"http://srv-s2b18-37-01.cms:9999","cpuUsage":1.05316105504731e+00,"sessionid":"","timestamp":"2023-08-16T08:22:53.002284Z"},{"context":"http://srv-s2b18-34-01.cms:9999","cpuUsage":1.08870707981704e+00,"sessionid":"","timestamp":"2023-08-16T08:22:49.765578Z"},{"context":"http://srv-s2b18-33-01.cms:9999","cpuUsage":1.14711335994217e+00,"sessionid":"","timestamp":"2023-08-16T08:22:46.813525Z"},{"context":"http://srv-s2b18-32-01.cms:9999","cpuUsage":1.12055398174378e+00,"sessionid":"","timestamp":"2023-08-16T08:22:46.769255Z"},{"context":"http://srv-s2b18-38-01.cms:9999","cpuUsage":1.16129032258064e+00,"sessionid":"","timestamp":"2023-08-16T08:22:54.694822Z"},{"context":"http://srv-s2b18-39-01.cms:9999","cpuUsage":1.17706300749040e+00,"sessionid":"","timestamp":"2023-08-16T08:22:49.964515Z"},{"context":"http://srv-s2b18-40-01.cms:9999","cpuUsage":3.61593655589124e+00,"sessionid":"","timestamp":"2023-08-16T08:22:46.402194Z"},{"context":"http://srv-s2b18-41-01.cms:9999","cpuUsage":1.14815979867883e+00,"sessionid":"","timestamp":"2023-08-16T08:22:45.743845Z"},{"context":"http://srv-s2b18-30-01.cms:9999","cpuUsage":1.18283629042406e+00,"sessionid":"","timestamp":"2023-08-16T08:22:45.405508Z"},{"context":"http://srv-s2b18-29-01.cms:9999","cpuUsage":1.13141400191225e+00,"sessionid":"","timestamp":"2023-08-16T08:22:48.732625Z"},{"context":"http://srv-s2b18-28-01.cms:9999","cpuUsage":1.16995848534407e+00,"sessionid":"","timestamp":"2023-08-16T08:22:49.388688Z"},{"context":"http://srv-s2b18-42-01.cms:9999","cpuUsage":1.01062228529652e+00,"sessionid":"","timestamp":"2023-08-16T08:22:48.266498Z"},{"context":"http://srv-s2b18-27-01.cms:9999","cpuUsage":1.09776044287871e+00,"sessionid":"","timestamp":"2023-08-16T08:22:54.802402Z"}]}}
